interpreter/README.md
interpreter/__init__.py
interpreter/cli.py
interpreter/code_block.py
interpreter/code_interpreter.py
interpreter/interpreter.py
interpreter/llama_2.py
interpreter/message_block.py
interpreter/system_message.txt
interpreter/utils.py
open_interpreter_bmo-0.1.2.dist-info/LICENSE
open_interpreter_bmo-0.1.2.dist-info/METADATA
open_interpreter_bmo-0.1.2.dist-info/WHEEL
open_interpreter_bmo-0.1.2.dist-info/entry_points.txt
open_interpreter_bmo-0.1.2.dist-info/RECORD
