Metadata-Version: 2.1
Name: open-interpreter-bmo
Version: 0.1.2
Summary: Let language models run code locally.
Author: Killian Lucas
Author-email: killian@drinkwater.ai
Requires-Python: >=3.10,<4.0
Classifier: Programming Language :: Python :: 3
Classifier: Programming Language :: Python :: 3.10
Classifier: Programming Language :: Python :: 3.11
Requires-Dist: appdirs (>=1.4.4,<2.0.0)
Requires-Dist: astor (>=0.8.1,<0.9.0)
Requires-Dist: git-python (>=1.0.3,<2.0.0)
Requires-Dist: inquirer (>=3.1.3,<4.0.0)
Requires-Dist: openai (>=0.27.8,<0.28.0)
Requires-Dist: pyreadline3 (>=3.4.1,<4.0.0) ; sys_platform == "win32"
Requires-Dist: python-dotenv (>=1.0.0,<2.0.0)
Requires-Dist: rich (>=13.4.2,<14.0.0)
Requires-Dist: six (>=1.16.0,<2.0.0)
Requires-Dist: tiktoken (>=0.4.0,<0.5.0)
Requires-Dist: tokentrim (>=0.1.9,<0.2.0)
Requires-Dist: wget (>=3.2,<4.0)
